simple_eda/__init__.py
simple_eda/simple_eda.py
SimpleEDA-0.0.1.dist-info/LICENSE
SimpleEDA-0.0.1.dist-info/METADATA
SimpleEDA-0.0.1.dist-info/WHEEL
SimpleEDA-0.0.1.dist-info/top_level.txt
SimpleEDA-0.0.1.dist-info/RECORD
